rushex/LICENSE
rushex/README.MD
rushex/__init__.py
rushex/requirements.txt
rushex/thirdparty.json
rushex-0.11.dist-info/LICENSE.rst
rushex-0.11.dist-info/METADATA
rushex-0.11.dist-info/WHEEL
rushex-0.11.dist-info/top_level.txt
rushex-0.11.dist-info/RECORD
