Metadata-Version: 2.1
Name: rushex
Version: 0.11
Summary: Search files using the fastest Regex Engine ever - ripgrep - Replacement is also supported!
Home-page: https://github.com/hansalemaos/rushex
Author: Johannes Fischer
Author-email: <aulasparticularesdealemaosp@gmail.com>
License: MIT
Keywords: ripgrep,grep,search,replace,regex,regular expressions,re
Classifier: Development Status :: 4 - Beta
Classifier: Programming Language :: Python :: 3 :: Only
Classifier: Programming Language :: Python :: 3.10
Classifier: Topic :: Scientific/Engineering :: Visualization
Classifier: Topic :: Software Development :: Libraries :: Python Modules
Classifier: Topic :: Utilities
License-File: LICENSE.rst
Requires-Dist: cppradixsort
Requires-Dist: downloadunzip
Requires-Dist: flatten-everything
Requires-Dist: list-all-files-recursively
Requires-Dist: numexpr
Requires-Dist: numpy
Requires-Dist: pandas
Requires-Dist: regex
Requires-Dist: search-in-syspath
Requires-Dist: textwrapre
Requires-Dist: touchtouch
Requires-Dist: ujson
